Metadata-Version: 2.1
Name: mojang-api
Version: 2.1.0
Summary: A full Python wrapper of Mojang's API and Authentication API.
Home-page: https://github.com/SynchronousX/mojang-api
Author: Synchronous
License: MIT
Keywords: mojang minecraft mc api authentication auth
Platform: UNKNOWN
Classifier: Development Status :: 4 - Beta
Classifier: Intended Audience :: Developers
Classifier: Topic :: Software Development :: Libraries :: Python Modules
Classifier: License :: OSI Approved :: MIT License
Classifier: Programming Language :: Python :: 3
Classifier: Programming Language :: Python :: 3.5
Classifier: Programming Language :: Python :: 3.6
Requires-Python: >=3.5.*
Requires-Dist: python-box
Requires-Dist: requests
